iris_cli/.env
iris_cli/.pytest_cache/.gitignore
iris_cli/.pytest_cache/CACHEDIR.TAG
iris_cli/.pytest_cache/README.md
iris_cli/.pytest_cache/v/cache/nodeids
iris_cli/.pytest_cache/v/cache/stepwise
iris_cli/__init__.py
iris_cli/main.py
iris_cli-0.0.1.dist-info/METADATA
iris_cli-0.0.1.dist-info/WHEEL
iris_cli-0.0.1.dist-info/entry_points.txt
iris_cli-0.0.1.dist-info/RECORD
